setup.py
django_plop/__init__.py
django_plop/middleware.py
django_plop.egg-info/PKG-INFO
django_plop.egg-info/SOURCES.txt
django_plop.egg-info/dependency_links.txt
django_plop.egg-info/requires.txt
django_plop.egg-info/top_level.txt