Metadata-Version: 1.0
Name: django-plop
Version: 0.0.1
Summary: Middleware for Django to support plop profiling
Home-page: https://github.com/brianhicks/django-plop
Author: Brian Hicks
Author-email: brian@brianthicks.com
License: UNKNOWN
Platform: UNKNOWN
Classifier: Development Status :: 4 - Beta
Classifier: Framework :: Django
Classifier: Intended Audience :: Developers
Classifier: License :: OSI Approved :: Apache Software License
Classifier: Programming Language :: Python :: 2.7
